setup.py
obs/__init__.py
obs/auth.py
obs/bucket.py
obs/client.py
obs/cloghandler.py
obs/const.py
obs/convertor.py
obs/ilog.py
obs/model.py
obs/portalocker.py
obs/transfer.py
obs/util.py
obssdk.egg-info/PKG-INFO
obssdk.egg-info/SOURCES.txt
obssdk.egg-info/dependency_links.txt
obssdk.egg-info/not-zip-safe
obssdk.egg-info/top_level.txt