Metadata-Version: 1.0
Name: obssdk
Version: 3.0.1
Summary: OBS Python SDK
Home-page: https://developer.huaweicloud.com/sdk?OBS
Author: HUAWEI
Author-email: esdk@huawei.com
License: GPL
Keywords: obs,python
Platform: Independant
